httpx_ntlm/__init__.py
httpx_ntlm/httpx_ntlm.py
httpx_ntlm-1.4.0.dist-info/LICENSE
httpx_ntlm-1.4.0.dist-info/METADATA
httpx_ntlm-1.4.0.dist-info/WHEEL
httpx_ntlm-1.4.0.dist-info/top_level.txt
httpx_ntlm-1.4.0.dist-info/RECORD
