Metadata-Version: 2.1
Name: httpx-ntlm
Version: 1.4.0
Summary: This package allows for HTTP NTLM authentication using the HTTPX library.
Home-page: https://github.com/ulodciv/httpx-ntlm
Author: Ludovic VAUGEOIS
Author-email: ulodciv@gmail.com
License: ISC
Classifier: Development Status :: 4 - Beta
Classifier: Intended Audience :: Developers
Classifier: Programming Language :: Python
Classifier: Programming Language :: Python :: 3.6
Classifier: Programming Language :: Python :: 3.7
Classifier: Programming Language :: Python :: 3.8
Classifier: Programming Language :: Python :: 3.9
Classifier: Programming Language :: Python :: 3.10
Classifier: Programming Language :: Python :: 3.11
Classifier: Programming Language :: Python :: 3.12
Classifier: License :: OSI Approved :: ISC License (ISCL)
Provides: httpx_ntlm
License-File: LICENSE
